bhimupipy/__init__.py
bhimupipy/app.py
bhimupipy/version.py
bhimupipy-0.0.2.dist-info/LICENSE
bhimupipy-0.0.2.dist-info/METADATA
bhimupipy-0.0.2.dist-info/WHEEL
bhimupipy-0.0.2.dist-info/entry_points.txt
bhimupipy-0.0.2.dist-info/top_level.txt
bhimupipy-0.0.2.dist-info/RECORD
