Metadata-Version: 2.1
Name: bhimupipy
Version: 0.0.2
Summary: A package to find upi details details
Home-page: https://github.com/shrikantbache/bhimupipy.git
Author: BACHE SHRIKANT GANGADHAR
Author-email: bacheshrikant@gmail.com
Maintainer: BACHE SHRIKANT GANGADHAR
Maintainer-email: bacheshrikant@gmail.com
License: MIT
Keywords: search,bhimupijs,brute,address,vpa,upi,spy
Platform: any
Classifier: Topic :: Utilities
Classifier: Natural Language :: English
Classifier: Operating System :: OS Independent
License-File: LICENSE
Requires-Dist: requests
